geoip_network/__init__.py
geoip_network/geoip_network.py
geoip_network/models.py
geoip_network-0.1.3.dist-info/LICENSE
geoip_network-0.1.3.dist-info/WHEEL
geoip_network-0.1.3.dist-info/METADATA
geoip_network-0.1.3.dist-info/RECORD
