Metadata-Version: 2.1
Name: geoip-network
Version: 0.1.3
Summary: The official python interface to GeoIP.Network
Home-page: https://geoip.network/
License: MIT
Keywords: geoip,localization,location,ip
Author: Tim Armstrong
Author-email: tim@plaintextnerds.com
Maintainer: Tim Armstrong
Maintainer-email: tim@plaintextnerds.com
Requires-Python: >=3.7,<4
Classifier: License :: OSI Approved :: MIT License
Classifier: Programming Language :: Python :: 3
Classifier: Programming Language :: Python :: 3.10
Classifier: Programming Language :: Python :: 3.7
Classifier: Programming Language :: Python :: 3.8
Classifier: Programming Language :: Python :: 3.9
Classifier: Programming Language :: Python :: Implementation
Classifier: Topic :: Internet
Classifier: Topic :: Software Development :: Libraries
Classifier: Topic :: Software Development :: Libraries :: Python Modules
Classifier: Topic :: Software Development :: Localization
Classifier: Topic :: System :: Networking :: Monitoring
Requires-Dist: requests (>=2.27.1,<3.0.0)
Project-URL: Repository, https://gitlab.com/geoip.network/python-library
